easyfactorlens/__init__.py
easyfactorlens/run_factor_test.py
utilities/__init__.py
utilities/_version.py
utilities/performance.py
utilities/plotting.py
utilities/tears.py
utilities/utils.py
easyfactorlens-1.0.1.dist-info/LICENSE.txt
easyfactorlens-1.0.1.dist-info/METADATA
easyfactorlens-1.0.1.dist-info/WHEEL
easyfactorlens-1.0.1.dist-info/top_level.txt
easyfactorlens-1.0.1.dist-info/RECORD
