Metadata-Version: 2.1
Name: easyfactorlens
Version: 1.0.1
Summary: Easyfactorlens是一个使用Ricequant数据，用Alphalens进行因子IC检验的封装工具。
Author: Zhang zeying, Cheng yichi, Wang weizhu
Author-email: vergilwong@foxmail.com
License: MIT
Platform: UNKNOWN
License-File: LICENSE.txt
